helloworld/__init__.py
helloworld/helloworld.py
GCBC_HelloWorld_1.0.0-1.0.0.dist-info/LICENSE
GCBC_HelloWorld_1.0.0-1.0.0.dist-info/METADATA
GCBC_HelloWorld_1.0.0-1.0.0.dist-info/WHEEL
GCBC_HelloWorld_1.0.0-1.0.0.dist-info/entry_points.txt
GCBC_HelloWorld_1.0.0-1.0.0.dist-info/top_level.txt
GCBC_HelloWorld_1.0.0-1.0.0.dist-info/RECORD
