Metadata-Version: 2.1
Name: GCBC-HelloWorld-1.0.0
Version: 1.0.0
Summary: An example of packaging code
Home-page: https://github.com/goodcodebadcode/pypi-helloworld
Author: David Ritchie
Author-email: david@goodcodebadcode.com
License: MIT
Platform: UNKNOWN
Classifier: License :: OSI Approved :: MIT License
Classifier: Programming Language :: Python :: 3
Classifier: Programming Language :: Python :: 3.7
License-File: LICENSE
Requires-Dist: click
Requires-Dist: requests
Requires-Dist: PyGithub (==1.53.0)
